<?xml version="1.0" encoding="UTF-8"?>
<language xmlns="http://www.woltlab.com" xmlns:xsi="http://www.w3.org/2001/XMLSchema-instance" xsi:schemaLocation="http://www.woltlab.com http://www.woltlab.com/XSD/2019/language.xsd" languagecode="de">
	<import>
		<category name="wcf.acp.option">
			<item name="wcf.acp.option.category.ha_steam"><![CDATA[Steam]]></item>
			<item name="wcf.acp.option.category.ha_steam.api"><![CDATA[API]]></item>
			<item name="wcf.acp.option.ha_steam_api_key"><![CDATA[Web-API-Schl端ssel]]></item>
			<item name="wcf.acp.option.ha_steam_api_key.description"><![CDATA[Vor der Benutzung der Steam-API muss der API-Schl端ssel eingef端gt werden. Der API-Schl端ssel kann <a href="https://steamcommunity.com/dev/apikey" class="externalURL" rel="nofollow"{if EXTERNAL_LINK_TARGET_BLANK} target="_blank"{/if}>hier</a> abgerufen werden.]]></item>
		</category>
		<category name="wcf.acp.group">
			<item name="wcf.acp.group.option.category.user.ha_steam"><![CDATA[Steam]]></item>
			<item name="wcf.acp.group.option.category.mod.ha_steam"><![CDATA[Steam]]></item>
			<item name="wcf.acp.group.option.category.admin.ha_steam"><![CDATA[Steam]]></item>
		</category>
	</import>
</language>
